crawler/__init__.py
crawler/search_crawler/__init__.py
crawler/search_crawler/crawler.py
crawler/searchclick_crawler/__init__.py
searchstax_simulator_crawler-0.0.1a23.dist-info/DESCRIPTION.rst
searchstax_simulator_crawler-0.0.1a23.dist-info/METADATA
searchstax_simulator_crawler-0.0.1a23.dist-info/RECORD
searchstax_simulator_crawler-0.0.1a23.dist-info/WHEEL
searchstax_simulator_crawler-0.0.1a23.dist-info/entry_points.txt
searchstax_simulator_crawler-0.0.1a23.dist-info/metadata.json
searchstax_simulator_crawler-0.0.1a23.dist-info/top_level.txt
