Metadata-Version: 2.0
Name: searchstax-simulator-crawler
Version: 0.0.1a23
Summary: Searchstax Simulator Crawler
Home-page: https://github.com/measuredsearch/searchstax-simulator-crawler
Author: Measured Search
Author-email: dev@measuredsearch.com
License: Apache License 2.0
Keywords: searchstax simulator
Platform: UNKNOWN
Classifier: Development Status :: 3 - Alpha
Classifier: Intended Audience :: Developers
Classifier: Topic :: System :: Distributed Computing
Classifier: License :: OSI Approved :: Apache Software License
Classifier: Programming Language :: Python :: 2
Classifier: Programming Language :: Python :: 2.7
Classifier: Programming Language :: Python :: 3
Classifier: Programming Language :: Python :: 3.3
Classifier: Programming Language :: Python :: 3.4
Classifier: Programming Language :: Python :: 3.5
Requires-Dist: Django (==1.8.13)
Requires-Dist: Markdown (==2.6.8)
Requires-Dist: coreapi (==2.3.0)
Requires-Dist: django-filter (==1.0.1)
Requires-Dist: djangorestframework (==3.6.2)
Requires-Dist: scrapy (==1.3.3)
Requires-Dist: unicodecsv
